odoo/addons/product_set/README.rst
odoo/addons/product_set/__init__.py
odoo/addons/product_set/__manifest__.py
odoo/addons/product_set/demo/product_set.xml
odoo/addons/product_set/demo/product_set_line.xml
odoo/addons/product_set/i18n/am.po
odoo/addons/product_set/i18n/ar.po
odoo/addons/product_set/i18n/bg.po
odoo/addons/product_set/i18n/bs.po
odoo/addons/product_set/i18n/ca.po
odoo/addons/product_set/i18n/cs.po
odoo/addons/product_set/i18n/da.po
odoo/addons/product_set/i18n/de.po
odoo/addons/product_set/i18n/el_GR.po
odoo/addons/product_set/i18n/en_GB.po
odoo/addons/product_set/i18n/es.po
odoo/addons/product_set/i18n/es_AR.po
odoo/addons/product_set/i18n/es_CL.po
odoo/addons/product_set/i18n/es_CO.po
odoo/addons/product_set/i18n/es_CR.po
odoo/addons/product_set/i18n/es_DO.po
odoo/addons/product_set/i18n/es_EC.po
odoo/addons/product_set/i18n/es_ES.po
odoo/addons/product_set/i18n/es_MX.po
odoo/addons/product_set/i18n/es_PE.po
odoo/addons/product_set/i18n/es_PY.po
odoo/addons/product_set/i18n/es_VE.po
odoo/addons/product_set/i18n/et.po
odoo/addons/product_set/i18n/eu.po
odoo/addons/product_set/i18n/fa.po
odoo/addons/product_set/i18n/fi.po
odoo/addons/product_set/i18n/fr.po
odoo/addons/product_set/i18n/fr_CA.po
odoo/addons/product_set/i18n/fr_CH.po
odoo/addons/product_set/i18n/fr_FR.po
odoo/addons/product_set/i18n/gl.po
odoo/addons/product_set/i18n/gl_ES.po
odoo/addons/product_set/i18n/he.po
odoo/addons/product_set/i18n/hr.po
odoo/addons/product_set/i18n/hr_HR.po
odoo/addons/product_set/i18n/hu.po
odoo/addons/product_set/i18n/id.po
odoo/addons/product_set/i18n/it.po
odoo/addons/product_set/i18n/ja.po
odoo/addons/product_set/i18n/ko.po
odoo/addons/product_set/i18n/lt.po
odoo/addons/product_set/i18n/lt_LT.po
odoo/addons/product_set/i18n/lv.po
odoo/addons/product_set/i18n/mk.po
odoo/addons/product_set/i18n/mn.po
odoo/addons/product_set/i18n/nb.po
odoo/addons/product_set/i18n/nb_NO.po
odoo/addons/product_set/i18n/nl.po
odoo/addons/product_set/i18n/nl_BE.po
odoo_addon_product_set-18.0.1.2.1.dist-info/METADATA
odoo_addon_product_set-18.0.1.2.1.dist-info/WHEEL
odoo_addon_product_set-18.0.1.2.1.dist-info/top_level.txt
odoo_addon_product_set-18.0.1.2.1.dist-info/RECORD
